pydvdid2/__init__.py
pydvdid2/crc64calculator.py
pydvdid2/crc64result.py
pydvdid2/exceptions.py
pydvdid2/functions.py
pydvdid2/py.typed
pydvdid2/test_crcresult64.py
pydvdid2/test_integration.py
pydvdid2-2.0.0.dist-info/licenses/LICENSE
pydvdid2-2.0.0.dist-info/METADATA
pydvdid2-2.0.0.dist-info/WHEEL
pydvdid2-2.0.0.dist-info/entry_points.txt
pydvdid2-2.0.0.dist-info/top_level.txt
pydvdid2-2.0.0.dist-info/RECORD
