Metadata-Version: 2.4
Name: pydvdid2
Version: 2.0.0
Summary: A pure Python implementation of the Windows API IDvdInfo2::GetDiscID method, as used by Windows Media Center to compute a 'practically unique' 64-bit CRC for metadata retrieval
Author-email: Sam Vervaeck <samvv@pm.me>, Steve Wood <octocat@nym.hush.com>
Maintainer-email: Sam Vervaeck <samvv@pm.me>
License-Expression: Apache-2.0
Project-URL: Homepage, https://github.com/samvv/pydvdid2
Project-URL: Bug Reports, https://github.com/samvv/pydvdid2/issues
Project-URL: Source, https://github.com/samvv/pydvdid2
Keywords: sample,setuptools,development
Classifier: Development Status :: 5 - Production/Stable
Classifier: Intended Audience :: Developers
Classifier: Natural Language :: English
Classifier: Operating System :: MacOS
Classifier: Operating System :: Microsoft :: Windows
Classifier: Operating System :: POSIX
Classifier: Topic :: Home Automation
Classifier: Topic :: Multimedia :: Video
Classifier: Topic :: Software Development :: Libraries :: Python Modules
Classifier: Topic :: Utilities
Classifier: Programming Language :: Python :: 3
Classifier: Programming Language :: Python :: 3.9
Classifier: Programming Language :: Python :: 3.10
Classifier: Programming Language :: Python :: 3.11
Classifier: Programming Language :: Python :: 3.12
Classifier: Programming Language :: Python :: 3.13
Classifier: Programming Language :: Python :: 3 :: Only
Requires-Python: >=3.9
License-File: LICENSE
Requires-Dist: pycdlib>=1.10.0
Requires-Dist: python-dateutil>=2.8.1
Provides-Extra: dev
Requires-Dist: check-manifest; extra == "dev"
Requires-Dist: pylint; extra == "dev"
Provides-Extra: test
Requires-Dist: coverage; extra == "test"
Requires-Dist: pytest; extra == "test"
Dynamic: license-file
